LICENSE.md
MANIFEST.in
README.md
__init__.py
requirements.txt
setup.py
version.py
gui/qt5/AlarmBoxControl.qml
gui/qt5/AlarmBoxView.qml
gui/qt5/AlarmButtonView.qml
gui/qt5/AlarmCard.qml
gui/qt5/AlarmsOverviewCard.qml
gui/qt5/AlarmsOverviewDelegate.qml
gui/qt5/ListView.qml
gui/qt5/RoundProgress.qml
gui/qt5/Timer.qml
gui/qt5/TimerCard.qml
gui/qt5/qmldir
gui/qt5/+mediacenter/RoundProgress.qml
gui/qt5/+mediacenter/Timer.qml
gui/qt5/+mediacenter/TimerCard.qml
gui/qt5/icons/close.svg
gui/qt5/icons/continue.svg
gui/qt5/icons/pause.svg
gui/qt5/sounds/clicked.wav
gui/qt5/translations/TimerCard_de.ts
gui/qt5/translations/TimerCard_es.ts
gui/qt5/translations/TimerCard_fr.ts
gui/qt5/translations/TimerCard_it.ts
gui/qt5/translations/TimerCard_nl.ts
gui/qt5/translations/TimerCard_pt.ts
gui/qt5/translations/skill-ovos-timer.openvoiceos_de.qm
gui/qt5/translations/skill-ovos-timer.openvoiceos_es.qm
gui/qt5/translations/skill-ovos-timer.openvoiceos_fr.qm
gui/qt5/translations/skill-ovos-timer.openvoiceos_it.qm
gui/qt5/translations/skill-ovos-timer.openvoiceos_nl.qm
gui/qt5/translations/skill-ovos-timer.openvoiceos_pt.qm
locale/ca-es/skill.json
locale/cs-cz/dialog/alarm_ask_time.dialog
locale/cs-cz/dialog/alarm_ocp_request.dialog
locale/cs-cz/dialog/alert_expiration_past.dialog
locale/cs-cz/dialog/alert_overlapping_ask.dialog
locale/cs-cz/dialog/alert_overlapping_duration_ask.dialog
locale/cs-cz/dialog/alert_prenotification.dialog
locale/cs-cz/dialog/alert_prenotification_ask.dialog
locale/cs-cz/dialog/alert_rescheduled.dialog
locale/cs-cz/dialog/alert_rescheduled_all_day.dialog
locale/cs-cz/dialog/alert_rescheduled_end.dialog
locale/cs-cz/dialog/alert_rescheduled_prenotification.dialog
locale/cs-cz/dialog/alert_rescheduled_repeat.dialog
locale/cs-cz/dialog/at_time.dialog
locale/cs-cz/dialog/confirm_alert_playback.dialog
locale/cs-cz/dialog/confirm_alert_recurring.dialog
locale/cs-cz/dialog/confirm_alert_recurring_playback.dialog
ovos_skill_alerts.egg-info/PKG-INFO
ovos_skill_alerts.egg-info/SOURCES.txt
ovos_skill_alerts.egg-info/dependency_links.txt
ovos_skill_alerts.egg-info/entry_points.txt
ovos_skill_alerts.egg-info/requires.txt
ovos_skill_alerts.egg-info/top_level.txt
