Metadata-Version: 2.1
Name: ovos-skill-alerts
Version: 0.1.14
Summary: UNKNOWN
Home-page: https://github.com/OpenVoiceOS/ovos-skill-alerts
Author: Emphasize,OpenVoiceOS
Author-email: 
License: BSD-3-Clause
Platform: UNKNOWN
Requires-Dist: json-database>=0.5
Requires-Dist: combo-lock>=0.2
Requires-Dist: ovos-utils>=0.0.32
Requires-Dist: ovos-bus-client<2.0.0,>=0.0.3
Requires-Dist: ovos-workshop<4.0.0,>=2.2.0
Requires-Dist: caldav~=1.2
Requires-Dist: icalendar~=5.0
Requires-Dist: ovos-utterance-normalizer<1.0.0,>=0.0.1
Requires-Dist: ovos-number-parser<1.0.0,>=0.0.1
Requires-Dist: ovos-date-parser<1.0.0,>=0.0.3
